{"error": false, "size": [1920, 1080], "name": "Aperture Dating Simulator", "version": "0.6.0alpha", "location": {"label": {"splashscreen": ["game/dictionaries/main.rpy", 31], "battle": ["game/story/endings/battle.rpy", 61], "cmdinput": ["game/story/endings/battle.rpy", 82], "cmddelete": ["game/story/endings/battle.rpy", 177], "cmdyield": ["game/story/endings/battle.rpy", 188], "estherturn": ["game/story/endings/battle.rpy", 202], "esthermove": ["game/story/endings/battle.rpy", 224], "es_move1": ["game/story/endings/battle.rpy", 238], "es_move2": ["game/story/endings/battle.rpy", 250], "es_move3": ["game/story/endings/battle.rpy", 259], "es_move4": ["game/story/endings/battle.rpy", 265], "esthertalk1": ["game/story/endings/battle.rpy", 276], "esthertalk2": ["game/story/endings/battle.rpy", 285], "esthertalk3": ["game/story/endings/battle.rpy", 294], "END_mcdeath": ["game/story/endings/battle.rpy", 315], "battleend": ["game/story/endings/battle.rpy", 339], "END_heartless": ["game/story/endings/battle.rpy", 349], "continuegame": ["game/story/endings/battle.rpy", 383], "day12": ["game/story/endings/boss.rpy", 4], "estherattack": ["game/story/endings/boss.rpy", 40], "enddecide_aceorunlikable": ["game/story/endings/boss.rpy", 94], "END_ace": ["game/story/endings/boss.rpy", 139], "END_unlikable": ["game/story/endings/boss.rpy", 144], "day12end": ["game/story/endings/boss.rpy", 152], "day13": ["game/story/endings/daythirteen.rpy", 1], "emmap": ["game/story/endings/daythirteen.rpy", 60], "unknownmissing": ["game/story/endings/daythirteen.rpy", 73], "saveaspen": ["game/story/endings/daythirteen.rpy", 93], "noaspen": ["game/story/endings/daythirteen.rpy", 168], "savegreg": ["game/story/endings/daythirteen.rpy", 185], "nogreg": ["game/story/endings/daythirteen.rpy", 288], "saverob": ["game/story/endings/daythirteen.rpy", 319], "norob": ["game/story/endings/daythirteen.rpy", 392], "saveccunknown": ["game/story/endings/daythirteen.rpy", 408], "nocc": ["game/story/endings/daythirteen.rpy", 543], "saveheath": ["game/story/endings/daythirteen.rpy", 566], "noheath": ["game/story/endings/daythirteen.rpy", 652], "savekris": ["game/story/endings/daythirteen.rpy", 669], "nokris": ["game/story/endings/daythirteen.rpy", 738], "escape_kris": ["game/story/endings/escape.rpy", 3], "escape_heath": ["game/story/endings/escape.rpy", 167], "escape_aspen": ["game/story/endings/escape.rpy", 338], "escape_ccunknown": ["game/story/endings/escape.rpy", 503], "leave_unknown": ["game/story/endings/escape.rpy", 513], "leave_cc": ["game/story/endings/escape.rpy", 716], "escape_rob": ["game/story/endings/escape.rpy", 918], "escape_gregory": ["game/story/endings/escape.rpy", 1087], "END_kristrue": ["game/story/endings/kristrue.rpy", 1], "END_heathtrue": ["game/story/endings/trueendings.rpy", 1], "END_aspentrue": ["game/story/endings/trueendings.rpy", 4], "END_cctrue": ["game/story/endings/trueendings.rpy", 7], "END_unknowntrue": ["game/story/endings/trueendings.rpy", 10], "END_robtrue": ["game/story/endings/trueendings.rpy", 13], "END_gregtrue": ["game/story/endings/trueendings.rpy", 16], "day5": ["game/story/week one/fifthday.rpy", 1], "krisday5": ["game/story/week one/fifthday.rpy", 92], "impresskris5": ["game/story/week one/fifthday.rpy", 136], "neutralkris5": ["game/story/week one/fifthday.rpy", 169], "offendkris5": ["game/story/week one/fifthday.rpy", 183], "krisday5cont": ["game/story/week one/fifthday.rpy", 198], "heathday5": ["game/story/week one/fifthday.rpy", 213], "impressheath5": ["game/story/week one/fifthday.rpy", 261], "offendheath5": ["game/story/week one/fifthday.rpy", 293], "neutralheath5": ["game/story/week one/fifthday.rpy", 314], "heathday5cont": ["game/story/week one/fifthday.rpy", 331], "aspenday5": ["game/story/week one/fifthday.rpy", 353], "impressaspen5": ["game/story/week one/fifthday.rpy", 419], "offendaspen5": ["game/story/week one/fifthday.rpy", 454], "ccday5": ["game/story/week one/fifthday.rpy", 483], "ccanduleave": ["game/story/week one/fifthday.rpy", 578], "ccanduresolve": ["game/story/week one/fifthday.rpy", 613], "ccday5cont": ["game/story/week one/fifthday.rpy", 688], "impresscc5": ["game/story/week one/fifthday.rpy", 723], "ccend5": ["game/story/week one/fifthday.rpy", 747], "neutralcc5": ["game/story/week one/fifthday.rpy", 777], "robday5": ["game/story/week one/fifthday.rpy", 784], "offendrob5": ["game/story/week one/fifthday.rpy", 844], "impressrob5": ["game/story/week one/fifthday.rpy", 888], "neutralrob5": ["game/story/week one/fifthday.rpy", 922], "day5end": ["game/story/week one/fifthday.rpy", 958], "e5first": ["game/story/week one/fifthdayemail.rpy", 72], "e5": ["game/story/week one/fifthdayemail.rpy", 80], "emailtwelve": ["game/story/week one/fifthdayemail.rpy", 85], "emailthirteen": ["game/story/week one/fifthdayemail.rpy", 90], "emailthirteenpt2": ["game/story/week one/fifthdayemail.rpy", 95], "emailfourteen": ["game/story/week one/fifthdayemail.rpy", 100], "start": ["game/story/week one/firstday.rpy", 4], "nameselect": ["game/story/week one/firstday.rpy", 37], "missing": ["game/story/week one/firstday.rpy", 73], "introcont": ["game/story/week one/firstday.rpy", 100], "krisday1": ["game/story/week one/firstday.rpy", 158], "offendkris": ["game/story/week one/firstday.rpy", 233], "impresskris": ["game/story/week one/firstday.rpy", 247], "krisday1cont": ["game/story/week one/firstday.rpy", 264], "heathday1": ["game/story/week one/firstday.rpy", 293], "impressheath": ["game/story/week one/firstday.rpy", 383], "offendheath": ["game/story/week one/firstday.rpy", 414], "heathday1cont": ["game/story/week one/firstday.rpy", 425], "unknownday1": ["game/story/week one/firstday.rpy", 449], "impressunknown": ["game/story/week one/firstday.rpy", 543], "offendunknown": ["game/story/week one/firstday.rpy", 574], "unknownday1cont": ["game/story/week one/firstday.rpy", 593], "aspenday1": ["game/story/week one/firstday.rpy", 645], "impressaspen": ["game/story/week one/firstday.rpy", 700], "offendaspen": ["game/story/week one/firstday.rpy", 720], "aspenday1cont": ["game/story/week one/firstday.rpy", 734], "ccday1": ["game/story/week one/firstday.rpy", 754], "ccchoice": ["game/story/week one/firstday.rpy", 850], "impresscc": ["game/story/week one/firstday.rpy", 888], "offendcc": ["game/story/week one/firstday.rpy", 919], "ccday1cont": ["game/story/week one/firstday.rpy", 941], "gregday1": ["game/story/week one/firstday.rpy", 948], "robday1": ["game/story/week one/firstday.rpy", 1015], "impressrob": ["game/story/week one/firstday.rpy", 1089], "offendrob": ["game/story/week one/firstday.rpy", 1104], "robday1cont": ["game/story/week one/firstday.rpy", 1123], "e1first": ["game/story/week one/firstdayemail.rpy", 72], "e1": ["game/story/week one/firstdayemail.rpy", 81], "emailone": ["game/story/week one/firstdayemail.rpy", 86], "emailtwo": ["game/story/week one/firstdayemail.rpy", 91], "emailthree": ["game/story/week one/firstdayemail.rpy", 96], "emailthreept2": ["game/story/week one/firstdayemail.rpy", 101], "day4": ["game/story/week one/fourthday.rpy", 1], "krisday4": ["game/story/week one/fourthday.rpy", 79], "impresskris4": ["game/story/week one/fourthday.rpy", 117], "offendkris4": ["game/story/week one/fourthday.rpy", 149], "krisday4cont": ["game/story/week one/fourthday.rpy", 169], "heathday4": ["game/story/week one/fourthday.rpy", 190], "impressheath4": ["game/story/week one/fourthday.rpy", 221], "neutralheath4": ["game/story/week one/fourthday.rpy", 238], "heathday4cont": ["game/story/week one/fourthday.rpy", 251], "offendheath4": ["game/story/week one/fourthday.rpy", 284], "estherday4": ["game/story/week one/fourthday.rpy", 308], "aspenday4": ["game/story/week one/fourthday.rpy", 351], "aspenday4cont": ["game/story/week one/fourthday.rpy", 400], "ccday4": ["game/story/week one/fourthday.rpy", 432], "impresscc4": ["game/story/week one/fourthday.rpy", 503], "offendcc4": ["game/story/week one/fourthday.rpy", 515], "ccday4cont": ["game/story/week one/fourthday.rpy", 535], "robday4": ["game/story/week one/fourthday.rpy", 559], "impressgreg": ["game/story/week one/fourthday.rpy", 612], "offendgreg": ["game/story/week one/fourthday.rpy", 632], "robday4cont": ["game/story/week one/fourthday.rpy", 647], "day4end": ["game/story/week one/fourthday.rpy", 694], "e4first": ["game/story/week one/fourthdayemail.rpy", 89], "e4": ["game/story/week one/fourthdayemail.rpy", 97], "emaileight": ["game/story/week one/fourthdayemail.rpy", 102], "emailnine": ["game/story/week one/fourthdayemail.rpy", 107], "emailninept2": ["game/story/week one/fourthdayemail.rpy", 112], "emailten": ["game/story/week one/fourthdayemail.rpy", 117], "emaileleven": ["game/story/week one/fourthdayemail.rpy", 122], "day2": ["game/story/week one/secondday.rpy", 1], "lockout": ["game/story/week one/secondday.rpy", 61], "letin": ["game/story/week one/secondday.rpy", 80], "silence": ["game/story/week one/secondday.rpy", 128], "estherday2": ["game/story/week one/secondday.rpy", 149], "krisday2": ["game/story/week one/secondday.rpy", 171], "impresskris2": ["game/story/week one/secondday.rpy", 213], "offendkris2": ["game/story/week one/secondday.rpy", 231], "krisday2cont": ["game/story/week one/secondday.rpy", 244], "heathday2": ["game/story/week one/secondday.rpy", 272], "heathmenuday2": ["game/story/week one/secondday.rpy", 307], "offendheath2": ["game/story/week one/secondday.rpy", 323], "impressheath2": ["game/story/week one/secondday.rpy", 340], "neutralheath": ["game/story/week one/secondday.rpy", 372], "heathday2cont": ["game/story/week one/secondday.rpy", 379], "whatswrong": ["game/story/week one/secondday.rpy", 408], "aspenday2": ["game/story/week one/secondday.rpy", 438], "impressaspen2": ["game/story/week one/secondday.rpy", 476], "offendaspen2": ["game/story/week one/secondday.rpy", 493], "bertha": ["game/story/week one/secondday.rpy", 511], "aspenfunny": ["game/story/week one/secondday.rpy", 534], "aspenday2cont": ["game/story/week one/secondday.rpy", 558], "ccday2": ["game/story/week one/secondday.rpy", 580], "impresscc2": ["game/story/week one/secondday.rpy", 605], "offendcc2": ["game/story/week one/secondday.rpy", 629], "ccday2cont": ["game/story/week one/secondday.rpy", 636], "robday2": ["game/story/week one/secondday.rpy", 654], "impressrob2": ["game/story/week one/secondday.rpy", 686], "offendrob2": ["game/story/week one/secondday.rpy", 712], "robday2cont": ["game/story/week one/secondday.rpy", 740], "e2first": ["game/story/week one/seconddayemail.rpy", 76], "e2": ["game/story/week one/seconddayemail.rpy", 84], "emailfour": ["game/story/week one/seconddayemail.rpy", 89], "emailfive": ["game/story/week one/seconddayemail.rpy", 94], "emailsix": ["game/story/week one/seconddayemail.rpy", 99], "emailsixpt2": ["game/story/week one/seconddayemail.rpy", 104], "day3": ["game/story/week one/thirdday.rpy", 1], "day3choice": ["game/story/week one/thirdday.rpy", 57], "day3choice2": ["game/story/week one/thirdday.rpy", 79], "uchooseagain": ["game/story/week one/thirdday.rpy", 95], "gchooseagain": ["game/story/week one/thirdday.rpy", 108], "krisday3": ["game/story/week one/thirdday.rpy", 124], "krisday3good": ["game/story/week one/thirdday.rpy", 169], "krisday3goodpt2": ["game/story/week one/thirdday.rpy", 235], "krisday3bad": ["game/story/week one/thirdday.rpy", 268], "heathday3": ["game/story/week one/thirdday.rpy", 286], "heathday3good": ["game/story/week one/thirdday.rpy", 336], "heathday3goodpt2": ["game/story/week one/thirdday.rpy", 397], "heathday3bad": ["game/story/week one/thirdday.rpy", 417], "aspenday3": ["game/story/week one/thirdday.rpy", 437], "aspenday3good": ["game/story/week one/thirdday.rpy", 489], "aspenday3goodpt2": ["game/story/week one/thirdday.rpy", 561], "aspenday3bad": ["game/story/week one/thirdday.rpy", 577], "ccday3": ["game/story/week one/thirdday.rpy", 591], "ccday3good": ["game/story/week one/thirdday.rpy", 642], "ccday3goodpt2": ["game/story/week one/thirdday.rpy", 695], "ccday3bad": ["game/story/week one/thirdday.rpy", 714], "robday3": ["game/story/week one/thirdday.rpy", 728], "rday3good": ["game/story/week one/thirdday.rpy", 786], "rday3goodpt2": ["game/story/week one/thirdday.rpy", 841], "rday3bad": ["game/story/week one/thirdday.rpy", 864], "day3end": ["game/story/week one/thirdday.rpy", 893], "e3first": ["game/story/week one/thirddayemail.rpy", 155], "e3": ["game/story/week one/thirddayemail.rpy", 164], "emailsevenkris": ["game/story/week one/thirddayemail.rpy", 169], "emailsevenheath": ["game/story/week one/thirddayemail.rpy", 174], "emailsevenaspen": ["game/story/week one/thirddayemail.rpy", 179], "emailsevencc": ["game/story/week one/thirddayemail.rpy", 184], "emailsevenrob": ["game/story/week one/thirddayemail.rpy", 189], "emailreport": ["game/story/week one/thirddayemail.rpy", 194], "emailreport2": ["game/story/week one/thirddayemail.rpy", 199], "day7end": ["game/story/week two/eighthday.rpy", 1], "day8": ["game/story/week two/eighthday.rpy", 16], "krisday8": ["game/story/week two/eighthday.rpy", 57], "p_krisday8": ["game/story/week two/eighthday.rpy", 75], "p_krisday8neutral": ["game/story/week two/eighthday.rpy", 113], "p_krisday8positive": ["game/story/week two/eighthday.rpy", 150], "n_krisday8": ["game/story/week two/eighthday.rpy", 182], "heathday8": ["game/story/week two/eighthday.rpy", 226], "p_heathday8": ["game/story/week two/eighthday.rpy", 269], "p_heathday8neutral": ["game/story/week two/eighthday.rpy", 287], "p_heathday8positive": ["game/story/week two/eighthday.rpy", 324], "n_heathday8": ["game/story/week two/eighthday.rpy", 370], "gregday8": ["game/story/week two/eighthday.rpy", 413], "impressgreg8": ["game/story/week two/eighthday.rpy", 475], "offendgreg8": ["game/story/week two/eighthday.rpy", 501], "aspenday8": ["game/story/week two/eighthday.rpy", 522], "p_aspenday8": ["game/story/week two/eighthday.rpy", 541], "p_aspenday8positive": ["game/story/week two/eighthday.rpy", 575], "p_aspenday8neutral": ["game/story/week two/eighthday.rpy", 599], "n_aspenday8": ["game/story/week two/eighthday.rpy", 619], "ccday8": ["game/story/week two/eighthday.rpy", 646], "p_ccday8": ["game/story/week two/eighthday.rpy", 692], "p_ccday8positive": ["game/story/week two/eighthday.rpy", 722], "p_ccday8neutral": ["game/story/week two/eighthday.rpy", 741], "n_ccday8": ["game/story/week two/eighthday.rpy", 758], "robday8": ["game/story/week two/eighthday.rpy", 783], "p_robday8": ["game/story/week two/eighthday.rpy", 799], "p_robday8neutral": ["game/story/week two/eighthday.rpy", 854], "p_robday8positive": ["game/story/week two/eighthday.rpy", 872], "n_robday8": ["game/story/week two/eighthday.rpy", 907], "day8end": ["game/story/week two/eighthday.rpy", 953], "e8first": ["game/story/week two/eighthdayemail.rpy", 73], "e8": ["game/story/week two/eighthdayemail.rpy", 81], "emailone_8": ["game/story/week two/eighthdayemail.rpy", 86], "emailtwo_8": ["game/story/week two/eighthdayemail.rpy", 91], "emailthree_8": ["game/story/week two/eighthdayemail.rpy", 96], "emailone_8pt2": ["game/story/week two/eighthdayemail.rpy", 101], "day11": ["game/story/week two/eleventhday.rpy", 1], "krisday11": ["game/story/week two/eleventhday.rpy", 73], "romancekrisday11": ["game/story/week two/eleventhday.rpy", 99], "p_krisday11": ["game/story/week two/eleventhday.rpy", 135], "n_krisday11": ["game/story/week two/eleventhday.rpy", 170], "heathday11": ["game/story/week two/eleventhday.rpy", 193], "romanceheathday11": ["game/story/week two/eleventhday.rpy", 261], "p_heathday11": ["game/story/week two/eleventhday.rpy", 298], "n_heathday11": ["game/story/week two/eleventhday.rpy", 329], "subromanceday11": ["game/story/week two/eleventhday.rpy", 354], "gregday11": ["game/story/week two/eleventhday.rpy", 377], "gregacceptance": ["game/story/week two/eleventhday.rpy", 443], "gregrejection": ["game/story/week two/eleventhday.rpy", 503], "unknownday11": ["game/story/week two/eleventhday.rpy", 531], "unknownacceptance": ["game/story/week two/eleventhday.rpy", 585], "unknownrejection": ["game/story/week two/eleventhday.rpy", 629], "aspenday11": ["game/story/week two/eleventhday.rpy", 655], "romanceaspenday11": ["game/story/week two/eleventhday.rpy", 680], "p_aspenday11": ["game/story/week two/eleventhday.rpy", 735], "n_aspenday11": ["game/story/week two/eleventhday.rpy", 782], "ccday11": ["game/story/week two/eleventhday.rpy", 808], "romanceccday11": ["game/story/week two/eleventhday.rpy", 831], "p_ccday11": ["game/story/week two/eleventhday.rpy", 886], "n_ccday11": ["game/story/week two/eleventhday.rpy", 943], "robday11": ["game/story/week two/eleventhday.rpy", 971], "romancerobday11": ["game/story/week two/eleventhday.rpy", 1007], "p_robday11": ["game/story/week two/eleventhday.rpy", 1053], "n_robday11": ["game/story/week two/eleventhday.rpy", 1089], "day11end": ["game/story/week two/eleventhday.rpy", 1123], "e11first": ["game/story/week two/eleventhdayemail.rpy", 41], "e11": ["game/story/week two/eleventhdayemail.rpy", 49], "emailone_11": ["game/story/week two/eleventhdayemail.rpy", 54], "emailtwo_11": ["game/story/week two/eleventhdayemail.rpy", 59], "day9": ["game/story/week two/ninthday.rpy", 1], "krisday9": ["game/story/week two/ninthday.rpy", 54], "p_krisday9": ["game/story/week two/ninthday.rpy", 86], "p_krisday9neutral": ["game/story/week two/ninthday.rpy", 116], "p_krisday9positive": ["game/story/week two/ninthday.rpy", 130], "n_krisday9": ["game/story/week two/ninthday.rpy", 148], "unknownday9": ["game/story/week two/ninthday.rpy", 178], "impressunknown9": ["game/story/week two/ninthday.rpy", 209], "offendunknown9": ["game/story/week two/ninthday.rpy", 244], "heathday9": ["game/story/week two/ninthday.rpy", 256], "p_heathday9": ["game/story/week two/ninthday.rpy", 293], "p_heathday9positive": ["game/story/week two/ninthday.rpy", 325], "p_heathday9neutral": ["game/story/week two/ninthday.rpy", 355], "n_heathday9": ["game/story/week two/ninthday.rpy", 372], "estherday9": ["game/story/week two/ninthday.rpy", 394], "estherday9positive": ["game/story/week two/ninthday.rpy", 418], "estherday9neutral": ["game/story/week two/ninthday.rpy", 425], "aspenday9": ["game/story/week two/ninthday.rpy", 431], "p_aspenday9": ["game/story/week two/ninthday.rpy", 453], "p_aspenday9positive": ["game/story/week two/ninthday.rpy", 480], "p_aspenday9neutral": ["game/story/week two/ninthday.rpy", 526], "n_aspenday9": ["game/story/week two/ninthday.rpy", 543], "estherday9pt2": ["game/story/week two/ninthday.rpy", 569], "ccday9": ["game/story/week two/ninthday.rpy", 601], "p_ccday9": ["game/story/week two/ninthday.rpy", 615], "p_ccday9positive": ["game/story/week two/ninthday.rpy", 643], "p_ccday9neutral": ["game/story/week two/ninthday.rpy", 690], "n_ccday9": ["game/story/week two/ninthday.rpy", 716], "robday9": ["game/story/week two/ninthday.rpy", 747], "p_robday9": ["game/story/week two/ninthday.rpy", 778], "n_robday9": ["game/story/week two/ninthday.rpy", 849], "day9end": ["game/story/week two/ninthday.rpy", 874], "e9first": ["game/story/week two/ninthdayemail.rpy", 172], "e9": ["game/story/week two/ninthdayemail.rpy", 180], "emailone_9": ["game/story/week two/ninthdayemail.rpy", 185], "emailtwo_9": ["game/story/week two/ninthdayemail.rpy", 190], "ekrisconf": ["game/story/week two/ninthdayemail.rpy", 195], "eheathconf": ["game/story/week two/ninthdayemail.rpy", 200], "easpenconf": ["game/story/week two/ninthdayemail.rpy", 205], "eccconf": ["game/story/week two/ninthdayemail.rpy", 210], "erobconf": ["game/story/week two/ninthdayemail.rpy", 215], "egregconf": ["game/story/week two/ninthdayemail.rpy", 220], "eunknownconf": ["game/story/week two/ninthdayemail.rpy", 225], "day10": ["game/story/week two/tenthday.rpy", 1], "day10choice": ["game/story/week two/tenthday.rpy", 71], "krisday10": ["game/story/week two/tenthday.rpy", 134], "krisconfession": ["game/story/week two/tenthday.rpy", 150], "krisacceptance": ["game/story/week two/tenthday.rpy", 222], "krisrejection": ["game/story/week two/tenthday.rpy", 307], "heathday10": ["game/story/week two/tenthday.rpy", 353], "heathacceptance": ["game/story/week two/tenthday.rpy", 411], "heathrejection": ["game/story/week two/tenthday.rpy", 498], "aspenday10": ["game/story/week two/tenthday.rpy", 536], "aspenacceptance": ["game/story/week two/tenthday.rpy", 602], "aspenrejection": ["game/story/week two/tenthday.rpy", 689], "ccday10": ["game/story/week two/tenthday.rpy", 743], "ccacceptance": ["game/story/week two/tenthday.rpy", 821], "ccrejection": ["game/story/week two/tenthday.rpy", 907], "robday10": ["game/story/week two/tenthday.rpy", 970], "robacceptance": ["game/story/week two/tenthday.rpy", 1037], "robrejection": ["game/story/week two/tenthday.rpy", 1123], "unlikableday10": ["game/story/week two/tenthday.rpy", 1188], "day10end": ["game/story/week two/tenthday.rpy", 1229], "endtest": ["game/story/week two/tenthday.rpy", 1249], "e10first": ["game/story/week two/tenthdayemail.rpy", 10], "day6": ["game/story/weekend/saturday.rpy", 1], "stay": ["game/story/weekend/saturday.rpy", 48], "wander": ["game/story/weekend/saturday.rpy", 63], "satoffice": ["game/story/weekend/saturday.rpy", 79], "satcafe": ["game/story/weekend/saturday.rpy", 102], "cafejello": ["game/story/weekend/saturday.rpy", 130], "biology": ["game/story/weekend/saturday.rpy", 142], "wheatleycameo": ["game/story/weekend/saturday.rpy", 162], "manufacture": ["game/story/weekend/saturday.rpy", 202], "recovery": ["game/story/weekend/saturday.rpy", 220], "satkris": ["game/story/weekend/saturday.rpy", 249], "satkrispos": ["game/story/weekend/saturday.rpy", 265], "satkrispos_pos": ["game/story/weekend/saturday.rpy", 321], "satkrispos_neg": ["game/story/weekend/saturday.rpy", 336], "satkrisneg": ["game/story/weekend/saturday.rpy", 353], "satheath": ["game/story/weekend/saturday.rpy", 375], "satheathpos": ["game/story/weekend/saturday.rpy", 404], "satheathpos_pos": ["game/story/weekend/saturday.rpy", 455], "satheathpos_neg": ["game/story/weekend/saturday.rpy", 469], "satheathneg": ["game/story/weekend/saturday.rpy", 483], "satcc": ["game/story/weekend/saturday.rpy", 498], "satccpos": ["game/story/weekend/saturday.rpy", 524], "satccpos_pos": ["game/story/weekend/saturday.rpy", 579], "satccpos_neg": ["game/story/weekend/saturday.rpy", 591], "satccneg": ["game/story/weekend/saturday.rpy", 604], "satgreg": ["game/story/weekend/saturday.rpy", 620], "satgreg_pos": ["game/story/weekend/saturday.rpy", 703], "sataspen": ["game/story/weekend/saturday.rpy", 773], "sataspenpos": ["game/story/weekend/saturday.rpy", 799], "sataspenpos_pos": ["game/story/weekend/saturday.rpy", 847], "sataspenpos_neg": ["game/story/weekend/saturday.rpy", 863], "sataspenneg": ["game/story/weekend/saturday.rpy", 881], "satrob": ["game/story/weekend/saturday.rpy", 898], "satrobpos": ["game/story/weekend/saturday.rpy", 916], "satrobpos_pos": ["game/story/weekend/saturday.rpy", 950], "satrobpos_neg": ["game/story/weekend/saturday.rpy", 977], "satrobneg": ["game/story/weekend/saturday.rpy", 993], "satunknown": ["game/story/weekend/saturday.rpy", 1016], "satunknownpos": ["game/story/weekend/saturday.rpy", 1033], "satunknownneg": ["game/story/weekend/saturday.rpy", 1160], "satend": ["game/story/weekend/saturdayend.rpy", 1], "satend_mc": ["game/story/weekend/saturdayend.rpy", 24], "satend_kris": ["game/story/weekend/saturdayend.rpy", 33], "satend_heath": ["game/story/weekend/saturdayend.rpy", 155], "satend_aspen": ["game/story/weekend/saturdayend.rpy", 269], "satend_rob": ["game/story/weekend/saturdayend.rpy", 364], "satend_cc": ["game/story/weekend/saturdayend.rpy", 492], "day7": ["game/story/weekend/sunday.rpy", 1], "day6stayend": ["game/story/weekend/sunday.rpy", 9], "day7cont": ["game/story/weekend/sunday.rpy", 19], "day7esther": ["game/story/weekend/sunday.rpy", 57], "day7plate": ["game/story/weekend/sunday.rpy", 255], "esthershootdown": ["game/story/weekend/sunday.rpy", 275], "day7alone": ["game/story/weekend/sunday.rpy", 297]}, "define": {"config.check_conflicting_properties": ["game/gui.rpy", 15], "gui.accent_color": ["game/gui.rpy", 28], "gui.idle_color": ["game/gui.rpy", 31], "gui.idle_small_color": ["game/gui.rpy", 35], "gui.hover_color": ["game/gui.rpy", 38], "gui.selected_color": ["game/gui.rpy", 42], "gui.insensitive_color": ["game/gui.rpy", 45], "gui.muted_color": ["game/gui.rpy", 49], "gui.hover_muted_color": ["game/gui.rpy", 50], "gui.text_color": ["game/gui.rpy", 53], "gui.interface_text_color": ["game/gui.rpy", 54], "gui.text_font": ["game/gui.rpy", 60], "gui.name_text_font": ["game/gui.rpy", 63], "gui.interface_text_font": ["game/gui.rpy", 66], "gui.text_size": ["game/gui.rpy", 69], "gui.name_text_size": ["game/gui.rpy", 72], "gui.interface_text_size": ["game/gui.rpy", 75], "gui.label_text_size": ["game/gui.rpy", 78], "gui.notify_text_size": ["game/gui.rpy", 81], "gui.title_text_size": ["game/gui.rpy", 84], "gui.main_menu_background": ["game/gui.rpy", 91], "gui.main_menu_background2": ["game/gui.rpy", 92], "gui.game_menu_background": ["game/gui.rpy", 93], "gui.textbox_height": ["game/gui.rpy", 102], "gui.textbox_yalign": ["game/gui.rpy", 106], "gui.name_xpos": ["game/gui.rpy", 111], "gui.name_ypos": ["game/gui.rpy", 112], "gui.name_xalign": ["game/gui.rpy", 116], "gui.namebox_width": ["game/gui.rpy", 120], "gui.namebox_height": ["game/gui.rpy", 121], "gui.namebox_borders": ["game/gui.rpy", 125], "gui.namebox_tile": ["game/gui.rpy", 129], "gui.dialogue_xpos": ["game/gui.rpy", 135], "gui.dialogue_ypos": ["game/gui.rpy", 136], "gui.dialogue_width": ["game/gui.rpy", 139], "gui.dialogue_text_xalign": ["game/gui.rpy", 143], "gui.button_width": ["game/gui.rpy", 152], "gui.button_height": ["game/gui.rpy", 153], "gui.button_borders": ["game/gui.rpy", 156], "gui.button_tile": ["game/gui.rpy", 160], "gui.button_text_font": ["game/gui.rpy", 163], "gui.button_text_size": ["game/gui.rpy", 166], "gui.button_text_idle_color": ["game/gui.rpy", 169], "gui.button_text_hover_color": ["game/gui.rpy", 170], "gui.button_text_selected_color": ["game/gui.rpy", 171], "gui.button_text_insensitive_color": ["game/gui.rpy", 172], "gui.button_text_xalign": ["game/gui.rpy", 176], "gui.radio_button_borders": ["game/gui.rpy", 185], "gui.check_button_borders": ["game/gui.rpy", 187], "gui.confirm_button_text_xalign": ["game/gui.rpy", 189], "gui.page_button_borders": ["game/gui.rpy", 191], "gui.quick_button_borders": ["game/gui.rpy", 193], "gui.quick_button_text_size": ["game/gui.rpy", 194], "gui.quick_button_text_idle_color": ["game/gui.rpy", 195], "gui.quick_button_text_selected_color": ["game/gui.rpy", 196], "gui.choice_button_width": ["game/gui.rpy", 209], "gui.choice_button_height": ["game/gui.rpy", 210], "gui.choice_button_tile": ["game/gui.rpy", 211], "gui.choice_button_borders": ["game/gui.rpy", 212], "gui.choice_button_text_font": ["game/gui.rpy", 213], "gui.choice_button_text_size": ["game/gui.rpy", 214], "gui.choice_button_text_xpos": ["game/gui.rpy", 215], "gui.choice_button_text_idle_color": ["game/gui.rpy", 216], "gui.choice_button_text_hover_color": ["game/gui.rpy", 217], "gui.choice_button_text_insensitive_color": ["game/gui.rpy", 218], "gui.navigation_xpos": ["game/gui.rpy", 244], "gui.skip_ypos": ["game/gui.rpy", 247], "gui.notify_ypos": ["game/gui.rpy", 250], "gui.choice_spacing": ["game/gui.rpy", 253], "gui.navigation_spacing": ["game/gui.rpy", 256], "gui.pref_spacing": ["game/gui.rpy", 259], "gui.pref_button_spacing": ["game/gui.rpy", 262], "gui.page_spacing": ["game/gui.rpy", 265], "gui.slot_spacing": ["game/gui.rpy", 268], "gui.main_menu_text_xalign": ["game/gui.rpy", 271], "gui.frame_borders": ["game/gui.rpy", 280], "gui.confirm_frame_borders": ["game/gui.rpy", 283], "gui.skip_frame_borders": ["game/gui.rpy", 286], "gui.notify_frame_borders": ["game/gui.rpy", 289], "gui.frame_tile": ["game/gui.rpy", 292], "gui.bar_size": ["game/gui.rpy", 304], "gui.scrollbar_size": ["game/gui.rpy", 305], "gui.slider_size": ["game/gui.rpy", 306], "gui.bar_tile": ["game/gui.rpy", 309], "gui.scrollbar_tile": ["game/gui.rpy", 310], "gui.slider_tile": ["game/gui.rpy", 311], "gui.bar_borders": ["game/gui.rpy", 314], "gui.scrollbar_borders": ["game/gui.rpy", 315], "gui.slider_borders": ["game/gui.rpy", 316], "gui.vbar_borders": ["game/gui.rpy", 319], "gui.vscrollbar_borders": ["game/gui.rpy", 320], "gui.vslider_borders": ["game/gui.rpy", 321], "gui.unscrollable": ["game/gui.rpy", 325], "config.history_length": ["game/gui.rpy", 333], "gui.history_height": ["game/gui.rpy", 337], "gui.history_spacing": ["game/gui.rpy", 340], "gui.history_name_xpos": ["game/gui.rpy", 344], "gui.history_name_ypos": ["game/gui.rpy", 345], "gui.history_name_width": ["game/gui.rpy", 346], "gui.history_name_xalign": ["game/gui.rpy", 347], "gui.history_text_xpos": ["game/gui.rpy", 350], "gui.history_text_ypos": ["game/gui.rpy", 351], "gui.history_text_width": ["game/gui.rpy", 352], "gui.history_text_xalign": ["game/gui.rpy", 353], "gui.nvl_borders": ["game/gui.rpy", 361], "gui.nvl_list_length": ["game/gui.rpy", 365], "gui.nvl_height": ["game/gui.rpy", 369], "gui.nvl_spacing": ["game/gui.rpy", 373], "gui.nvl_name_xpos": ["game/gui.rpy", 377], "gui.nvl_name_ypos": ["game/gui.rpy", 378], "gui.nvl_name_width": ["game/gui.rpy", 379], "gui.nvl_name_xalign": ["game/gui.rpy", 380], "gui.nvl_text_xpos": ["game/gui.rpy", 383], "gui.nvl_text_ypos": ["game/gui.rpy", 384], "gui.nvl_text_width": ["game/gui.rpy", 385], "gui.nvl_text_xalign": ["game/gui.rpy", 386], "gui.nvl_thought_xpos": ["game/gui.rpy", 390], "gui.nvl_thought_ypos": ["game/gui.rpy", 391], "gui.nvl_thought_width": ["game/gui.rpy", 392], "gui.nvl_thought_xalign": ["game/gui.rpy", 393], "gui.nvl_button_xpos": ["game/gui.rpy", 396], "gui.nvl_button_xalign": ["game/gui.rpy", 397], "gui.language": ["game/gui.rpy", 406], "cutscenechoice": ["game/screens.rpy", 253], "quick_menu": ["game/screens.rpy", 332], "mm2": ["game/screens.rpy", 389], "gui.history_allow_tags": ["game/screens.rpy", 918], "config.nvl_list_length": ["game/screens.rpy", 1352], "bubble.frame": ["game/screens.rpy", 1461], "bubble.thoughtframe": ["game/screens.rpy", 1462], "bubble.properties": ["game/screens.rpy", 1464], "bubble.expand_area": ["game/screens.rpy", 1490], "config.default_music_volume": ["game/dictionaries/audio.rpy", 1], "config.auto_voice": ["game/dictionaries/characters.rpy", 1], "begmc": ["game/dictionaries/characters.rpy", 3], "d": ["game/dictionaries/characters.rpy", 5], "n": ["game/dictionaries/characters.rpy", 7], "e": ["game/dictionaries/characters.rpy", 8], "mc": ["game/dictionaries/characters.rpy", 10], "mccut": ["game/dictionaries/characters.rpy", 11], "k": ["game/dictionaries/characters.rpy", 13], "h": ["game/dictionaries/characters.rpy", 15], "u": ["game/dictionaries/characters.rpy", 17], "ry": ["game/dictionaries/characters.rpy", 18], "a": ["game/dictionaries/characters.rpy", 20], "acg": ["game/dictionaries/characters.rpy", 21], "cu": ["game/dictionaries/characters.rpy", 23], "c": ["game/dictionaries/characters.rpy", 24], "ccg": ["game/dictionaries/characters.rpy", 25], "gu": ["game/dictionaries/characters.rpy", 27], "g": ["game/dictionaries/characters.rpy", 28], "g1": ["game/dictionaries/characters.rpy", 29], "g2": ["game/dictionaries/characters.rpy", 30], "g3": ["game/dictionaries/characters.rpy", 31], "gall": ["game/dictionaries/characters.rpy", 32], "r": ["game/dictionaries/characters.rpy", 34], "rcg": ["game/dictionaries/characters.rpy", 35], "wu": ["game/dictionaries/characters.rpy", 37], "w": ["game/dictionaries/characters.rpy", 38], "cw": ["game/dictionaries/characters.rpy", 40], "bar": ["game/dictionaries/characters.rpy", 41], "ann": ["game/dictionaries/characters.rpy", 42], "stc": ["game/dictionaries/characters.rpy", 43], "intc": ["game/dictionaries/characters.rpy", 44], "vc": ["game/dictionaries/characters.rpy", 45], "vc2": ["game/dictionaries/characters.rpy", 46], "dc": ["game/dictionaries/characters.rpy", 47], "tg": ["game/dictionaries/characters.rpy", 48], "cutscenetextbox": ["game/dictionaries/main.rpy", 44], "savequestionpopup": ["game/dictionaries/main.rpy", 46], "plant": ["game/dictionaries/main.rpy", 49], "ball": ["game/dictionaries/main.rpy", 50], "picture": ["game/dictionaries/main.rpy", 51], "spades": ["game/dictionaries/main.rpy", 52], "emailfromunknownday2": ["game/dictionaries/main.rpy", 53], "askforu": ["game/dictionaries/main.rpy", 54], "askforg": ["game/dictionaries/main.rpy", 55], "giveccpicture": ["game/dictionaries/main.rpy", 56], "cctv": ["game/dictionaries/main.rpy", 57], "knowabtwaterfall": ["game/dictionaries/main.rpy", 58], "cactusname": ["game/dictionaries/main.rpy", 59], "battle": ["game/dictionaries/main.rpy", 60], "aspenknowabtbertha": ["game/dictionaries/main.rpy", 61], "krisgoodbye": ["game/dictionaries/main.rpy", 64], "heathgoodbye": ["game/dictionaries/main.rpy", 65], "unknownhumor": ["game/dictionaries/main.rpy", 66], "aspengoodbye": ["game/dictionaries/main.rpy", 67], "haveaheart": ["game/dictionaries/main.rpy", 68], "goodday3": ["game/dictionaries/main.rpy", 71], "day6stay": ["game/dictionaries/main.rpy", 72], "satchoose_kris": ["game/dictionaries/main.rpy", 73], "satchoose_heath": ["game/dictionaries/main.rpy", 74], "satchoose_aspen": ["game/dictionaries/main.rpy", 75], "satchoose_cc": ["game/dictionaries/main.rpy", 76], "satchoose_rob": ["game/dictionaries/main.rpy", 77], "wkd3": ["game/dictionaries/main.rpy", 128], "whd3": ["game/dictionaries/main.rpy", 129], "wad3": ["game/dictionaries/main.rpy", 130], "wcd3": ["game/dictionaries/main.rpy", 131], "wrd3": ["game/dictionaries/main.rpy", 132], "tshirt": ["game/dictionaries/main.rpy", 135], "formal": ["game/dictionaries/main.rpy", 136], "uniform": ["game/dictionaries/main.rpy", 137], "vaca": ["game/dictionaries/main.rpy", 138], "askestherday2": ["game/dictionaries/main.rpy", 139], "emailfromgregday9": ["game/dictionaries/main.rpy", 149], "emailfromunknownday9": ["game/dictionaries/main.rpy", 150], "lock_kris": ["game/dictionaries/main.rpy", 155], "lock_heath": ["game/dictionaries/main.rpy", 156], "lock_aspen": ["game/dictionaries/main.rpy", 157], "lock_cc": ["game/dictionaries/main.rpy", 158], "lock_rob": ["game/dictionaries/main.rpy", 159], "lock_gregory": ["game/dictionaries/main.rpy", 160], "lock_unknown": ["game/dictionaries/main.rpy", 161], "romance_points": ["game/dictionaries/main.rpy", 164], "positive": ["game/dictionaries/main.rpy", 173], "priority": ["game/dictionaries/main.rpy", 182], "romance_minimum_for_good_ending": ["game/dictionaries/main.rpy", 193], "romance_minimum_for_true_ending": ["game/dictionaries/main.rpy", 194], "esther_affection": ["game/dictionaries/main.rpy", 196], "gentleswitch": ["game/dictionaries/transforms.rpy", 33], "vigswitch": ["game/dictionaries/transforms.rpy", 34], "gallswitch": ["game/dictionaries/transforms.rpy", 35], "selected_char": ["game/menus/gallery.rpy", 10], "gui.slot_button_text_selected_hover_color": ["game/menus/loadsave.rpy", 14], "config.thumbnail_width": ["game/menus/loadsave.rpy", 15], "config.thumbnail_height": ["game/menus/loadsave.rpy", 16], "gui.file_slot_cols": ["game/menus/loadsave.rpy", 18], "gui.file_slot_rows": ["game/menus/loadsave.rpy", 19], "config.name": ["game/options.rpy", 15], "gui.show_name": ["game/options.rpy", 21], "config.version": ["game/options.rpy", 26], "gui.show_version": ["game/options.rpy", 28], "gui.about": ["game/options.rpy", 32], "build.name": ["game/options.rpy", 40], "config.has_sound": ["game/options.rpy", 49], "config.has_music": ["game/options.rpy", 50], "config.has_voice": ["game/options.rpy", 51], "config.main_menu_music": ["game/options.rpy", 53], "config.enter_transition": ["game/options.rpy", 63], "config.exit_transition": ["game/options.rpy", 64], "config.intra_transition": ["game/options.rpy", 69], "config.after_load_transition": ["game/options.rpy", 74], "config.end_game_transition": ["game/options.rpy", 79], "config.window": ["game/options.rpy", 96], "config.window_show_transition": ["game/options.rpy", 101], "config.window_hide_transition": ["game/options.rpy", 102], "config.save_directory": ["game/options.rpy", 133], "config.has_autosave": ["game/options.rpy", 134], "config.window_icon": ["game/options.rpy", 141], "daynum": ["game/story/daytransitions.rpy", 1], "dayday": ["game/story/daytransitions.rpy", 2], "timeofday": ["game/story/daytransitions.rpy", 3], "ap_count": ["game/story/endings/battle.rpy", 1], "mc_health": ["game/story/endings/battle.rpy", 2], "es_health": ["game/story/endings/battle.rpy", 3], "terminaltext": ["game/story/endings/battle.rpy", 4], "esther_stunned": ["game/story/endings/battle.rpy", 5], "mc_poisoned": ["game/story/endings/battle.rpy", 6], "mc_poisonedcount": ["game/story/endings/battle.rpy", 7], "cmdexecuted": ["game/story/endings/battle.rpy", 8], "mc_turn": ["game/story/endings/battle.rpy", 9], "es_turn": ["game/story/endings/battle.rpy", 10], "times_talked": ["game/story/endings/battle.rpy", 11], "printthisround": ["game/story/endings/battle.rpy", 12], "aceending": ["game/story/endings/boss.rpy", 2], "unlikableending": ["game/story/endings/boss.rpy", 3], "emv_kris": ["game/story/endings/emergencymap.rpy", 2], "emv_heath": ["game/story/endings/emergencymap.rpy", 3], "emv_cc": ["game/story/endings/emergencymap.rpy", 4], "emv_greg": ["game/story/endings/emergencymap.rpy", 5], "emv_rob": ["game/story/endings/emergencymap.rpy", 6], "emv_aspen": ["game/story/endings/emergencymap.rpy", 7], "emv_unknown": ["game/story/endings/emergencymap.rpy", 8], "blindplayer": ["game/story/endings/escape.rpy", 1], "config.layers": ["game/story/week one/firstday.rpy", 1], "name": ["game/story/week one/firstday.rpy", 33], "krischooseagain": ["game/story/week two/tenthday.rpy", 65], "heathchooseagain": ["game/story/week two/tenthday.rpy", 66], "aspenchooseagain": ["game/story/week two/tenthday.rpy", 67], "ccchooseagain": ["game/story/week two/tenthday.rpy", 68], "robchooseagain": ["game/story/week two/tenthday.rpy", 69], "cores_visited": ["game/story/weekend/map.rpy", 3], "v_satoffice": ["game/story/weekend/map.rpy", 5], "v_recovery": ["game/story/weekend/map.rpy", 6], "v_satcafe": ["game/story/weekend/map.rpy", 7], "v_kris": ["game/story/weekend/map.rpy", 8], "inv_kris": ["game/story/weekend/map.rpy", 9], "v_heath": ["game/story/weekend/map.rpy", 10], "inv_heath": ["game/story/weekend/map.rpy", 11], "v_cc": ["game/story/weekend/map.rpy", 12], "inv_cc": ["game/story/weekend/map.rpy", 13], "informed_about_canister": ["game/story/weekend/map.rpy", 14], "v_greg": ["game/story/weekend/map.rpy", 15], "v_rob": ["game/story/weekend/map.rpy", 16], "inv_rob": ["game/story/weekend/map.rpy", 17], "v_aspen": ["game/story/weekend/map.rpy", 18], "inv_aspen": ["game/story/weekend/map.rpy", 19], "v_unknown": ["game/story/weekend/map.rpy", 20], "v_biology": ["game/story/weekend/map.rpy", 22], "v_manufacture": ["game/story/weekend/map.rpy", 24], "v_wheatley": ["game/story/weekend/map.rpy", 25]}, "screen": {"cuttextbox": ["game/screens.rpy", 105], "say": ["game/screens.rpy", 108], "input": ["game/screens.rpy", 205], "choice": ["game/screens.rpy", 255], "quick_menu": ["game/screens.rpy", 1568], "navigation": ["game/screens.rpy", 353], "main_menu": ["game/screens.rpy", 391], "game_menu": ["game/screens.rpy", 514], "about": ["game/screens.rpy", 648], "preferences": ["game/screens.rpy", 718], "history": ["game/screens.rpy", 878], "help": ["game/screens.rpy", 966], "keyboard_help": ["game/screens.rpy", 995], "mouse_help": ["game/screens.rpy", 1046], "gamepad_help": ["game/screens.rpy", 1069], "confirm": ["game/screens.rpy", 1134], "skip_indicator": ["game/screens.rpy", 1215], "notify": ["game/screens.rpy", 1260], "nvl": ["game/screens.rpy", 1299], "nvl_dialogue": ["game/screens.rpy", 1331], "bubble": ["game/screens.rpy", 1419], "disable_arrows": ["game/dictionaries/main.rpy", 21], "vignette": ["game/dictionaries/transforms.rpy", 42], "galleryk": ["game/menus/gallery.rpy", 23], "galleryh": ["game/menus/gallery.rpy", 53], "gallerya": ["game/menus/gallery.rpy", 80], "galleryc": ["game/menus/gallery.rpy", 106], "galleryr": ["game/menus/gallery.rpy", 134], "galleryg": ["game/menus/gallery.rpy", 160], "galleryu": ["game/menus/gallery.rpy", 184], "fullcutscene1": ["game/menus/gallery.rpy", 210], "fullcutscene2": ["game/menus/gallery.rpy", 215], "fullcutscene3": ["game/menus/gallery.rpy", 220], "fullcutscene4": ["game/menus/gallery.rpy", 225], "save": ["game/menus/loadsave.rpy", 1], "load": ["game/menus/loadsave.rpy", 8], "behindoverlay": ["game/menus/loadsave.rpy", 21], "file_slots": ["game/menus/loadsave.rpy", 24], "pref_audio": ["game/menus/preferences.rpy", 34], "pref_video": ["game/menus/preferences.rpy", 60], "pref_other": ["game/menus/preferences.rpy", 119], "deletenotif": ["game/menus/preferences.rpy", 141], "mmnotif": ["game/menus/preferences.rpy", 157], "quitnotif": ["game/menus/preferences.rpy", 173], "pref_open": ["game/menus/preferences.rpy", 190], "pausemenu": ["game/menus/preferences.rpy", 193], "aboutmenu": ["game/menus/preferences.rpy", 203], "disclaimers": ["game/menus/preferences.rpy", 237], "aboutcredits": ["game/menus/preferences.rpy", 259], "affectionprogress": ["game/menus/romancebars.rpy", 9], "daytransition": ["game/story/daytransitions.rpy", 22], "timeskip": ["game/story/daytransitions.rpy", 38], "creditsfadeout": ["game/story/daytransitions.rpy", 42], "truedaytransition": ["game/story/daytransitions.rpy", 45], "main": ["game/story/endings/battle.rpy", 24], "disable_Lmouse": ["game/story/endings/battle.rpy", 54], "esther_speak": ["game/story/endings/battle.rpy", 304], "esther_print": ["game/story/endings/battle.rpy", 307], "esther_win": ["game/story/endings/battle.rpy", 310], "esther_win2": ["game/story/endings/battle.rpy", 312], "savequestion": ["game/story/endings/boss.rpy", 79], "emergencymap": ["game/story/endings/emergencymap.rpy", 12], "emergencymapup": ["game/story/endings/emergencymap.rpy", 48], "emergencymapdown": ["game/story/endings/emergencymap.rpy", 61], "emailday5": ["game/story/week one/fifthdayemail.rpy", 1], "email12": ["game/story/week one/fifthdayemail.rpy", 12], "email13": ["game/story/week one/fifthdayemail.rpy", 27], "email13pt2": ["game/story/week one/fifthdayemail.rpy", 42], "email14": ["game/story/week one/fifthdayemail.rpy", 57], "emailday1": ["game/story/week one/firstdayemail.rpy", 1], "email1": ["game/story/week one/firstdayemail.rpy", 12], "email2": ["game/story/week one/firstdayemail.rpy", 27], "email3": ["game/story/week one/firstdayemail.rpy", 42], "email3pt2": ["game/story/week one/firstdayemail.rpy", 57], "emailday4": ["game/story/week one/fourthdayemail.rpy", 1], "email8": ["game/story/week one/fourthdayemail.rpy", 13], "email9": ["game/story/week one/fourthdayemail.rpy", 28], "email9pt2": ["game/story/week one/fourthdayemail.rpy", 43], "email10": ["game/story/week one/fourthdayemail.rpy", 58], "email11": ["game/story/week one/fourthdayemail.rpy", 73], "emailday2": ["game/story/week one/seconddayemail.rpy", 1], "email4": ["game/story/week one/seconddayemail.rpy", 12], "email5": ["game/story/week one/seconddayemail.rpy", 30], "email6": ["game/story/week one/seconddayemail.rpy", 45], "email6pt2": ["game/story/week one/seconddayemail.rpy", 60], "emailday3": ["game/story/week one/thirddayemail.rpy", 1], "email7kris": ["game/story/week one/thirddayemail.rpy", 30], "email7heath": ["game/story/week one/thirddayemail.rpy", 45], "email7aspen": ["game/story/week one/thirddayemail.rpy", 60], "email7cc": ["game/story/week one/thirddayemail.rpy", 75], "email7rob": ["game/story/week one/thirddayemail.rpy", 90], "emailrep": ["game/story/week one/thirddayemail.rpy", 107], "emailrep2": ["game/story/week one/thirddayemail.rpy", 124], "emailday8": ["game/story/week two/eighthdayemail.rpy", 1], "email1_8": ["game/story/week two/eighthdayemail.rpy", 13], "email2_8": ["game/story/week two/eighthdayemail.rpy", 28], "email3_8": ["game/story/week two/eighthdayemail.rpy", 43], "email1_8pt2": ["game/story/week two/eighthdayemail.rpy", 58], "emailday11": ["game/story/week two/eleventhdayemail.rpy", 1], "email1_11": ["game/story/week two/eleventhdayemail.rpy", 11], "email2_11": ["game/story/week two/eleventhdayemail.rpy", 26], "emailday9": ["game/story/week two/ninthdayemail.rpy", 1], "email1_9": ["game/story/week two/ninthdayemail.rpy", 37], "email2_9": ["game/story/week two/ninthdayemail.rpy", 52], "krisconfemail": ["game/story/week two/ninthdayemail.rpy", 67], "heathconfemail": ["game/story/week two/ninthdayemail.rpy", 82], "aspenconfemail": ["game/story/week two/ninthdayemail.rpy", 97], "ccconfemail": ["game/story/week two/ninthdayemail.rpy", 112], "robconfemail": ["game/story/week two/ninthdayemail.rpy", 127], "gregconfemail": ["game/story/week two/ninthdayemail.rpy", 142], "unknownconfemail": ["game/story/week two/ninthdayemail.rpy", 157], "emailday10": ["game/story/week two/tenthdayemail.rpy", 1], "aptmap": ["game/story/weekend/map.rpy", 29], "aptmapup": ["game/story/weekend/map.rpy", 53], "aptmapdown": ["game/story/weekend/map.rpy", 66]}, "transform": {"delayed_blink": ["game/screens.rpy", 1222], "notify_appear": ["game/screens.rpy", 1271], "bounce": ["game/dictionaries/transforms.rpy", 1], "tilted": ["game/dictionaries/transforms.rpy", 5], "tilted2": ["game/dictionaries/transforms.rpy", 8], "ab_tilt": ["game/dictionaries/transforms.rpy", 11], "save_tilt": ["game/dictionaries/transforms.rpy", 14], "cred_tilt": ["game/dictionaries/transforms.rpy", 17], "disc_tilt": ["game/dictionaries/transforms.rpy", 20], "delete_tilt": ["game/dictionaries/transforms.rpy", 23], "daydiss": ["game/dictionaries/transforms.rpy", 26], "gallery_size": ["game/dictionaries/transforms.rpy", 30], "emaildiss": ["game/dictionaries/transforms.rpy", 37], "splashfadeout": ["game/dictionaries/transforms.rpy", 45], "fade_in_text": ["game/dictionaries/transforms.rpy", 49]}, "callable": {"touch": ["game/gui.rpy", 418], "small": ["game/gui.rpy", 425], "audio_crossFade": ["game/dictionaries/audio.rpy", 13], "sfx_crossFade": ["game/dictionaries/audio.rpy", 32], "reset_data": ["game/menus/preferences.rpy", 19], "DispTextStyle.__init__": ["game/kinetic_text_tags.rpy", 63], "DispTextStyle.add_tags": ["game/kinetic_text_tags.rpy", 67], "DispTextStyle.apply_style": ["game/kinetic_text_tags.rpy", 84], "DispTextStyle.start_tags": ["game/kinetic_text_tags.rpy", 95], "DispTextStyle.end_tags": ["game/kinetic_text_tags.rpy", 114], "BounceText.__init__": ["game/kinetic_text_tags.rpy", 130], "BounceText.render": ["game/kinetic_text_tags.rpy", 145], "BounceText.event": ["game/kinetic_text_tags.rpy", 167], "BounceText.visit": ["game/kinetic_text_tags.rpy", 170], "FadeInText.__init__": ["game/kinetic_text_tags.rpy", 177], "FadeInText.render": ["game/kinetic_text_tags.rpy", 192], "FadeInText.visit": ["game/kinetic_text_tags.rpy", 211], "ScareText.__init__": ["game/kinetic_text_tags.rpy", 216], "ScareText.render": ["game/kinetic_text_tags.rpy", 224], "ScareText.visit": ["game/kinetic_text_tags.rpy", 237], "ChaosText.__init__": ["game/kinetic_text_tags.rpy", 252], "ChaosText.render": ["game/kinetic_text_tags.rpy", 261], "ChaosText.visit": ["game/kinetic_text_tags.rpy", 298], "RotateText.__init__": ["game/kinetic_text_tags.rpy", 303], "RotateText.render": ["game/kinetic_text_tags.rpy", 310], "RotateText.visit": ["game/kinetic_text_tags.rpy", 326], "SwapText.__init__": ["game/kinetic_text_tags.rpy", 388], "SwapText.render": ["game/kinetic_text_tags.rpy", 405], "SwapText.visit": ["game/kinetic_text_tags.rpy", 428], "MoveText.__init__": ["game/kinetic_text_tags.rpy", 437], "MoveText.render": ["game/kinetic_text_tags.rpy", 444], "MoveText.event": ["game/kinetic_text_tags.rpy", 466], "MoveText.visit": ["game/kinetic_text_tags.rpy", 471], "bounce_tag": ["game/kinetic_text_tags.rpy", 486], "fade_in_tag": ["game/kinetic_text_tags.rpy", 540], "scare_tag": ["game/kinetic_text_tags.rpy", 579], "chaos_tag": ["game/kinetic_text_tags.rpy", 607], "rotate_tag": ["game/kinetic_text_tags.rpy", 626], "swap_tag": ["game/kinetic_text_tags.rpy", 661], "move_tag": ["game/kinetic_text_tags.rpy", 687], "paragraph_tag": ["game/kinetic_text_tags.rpy", 714], "omega_tag": ["game/kinetic_text_tags.rpy", 736]}}, "build": {"directory_name": "ads-0.6.0alpha", "executable_name": "ads", "include_update": false, "packages": [{"name": "gameonly", "formats": ["null"], "file_lists": ["all"], "description": "Game-Only Update for Mobile", "update": true, "dlc": false, "hidden": true}, {"name": "pc", "formats": ["zip"], "file_lists": ["windows", "linux", "renpy", "all"], "description": "PC: Windows and Linux", "update": true, "dlc": false, "hidden": false}, {"name": "linux", "formats": ["tar.bz2"], "file_lists": ["linux", "linux_arm", "renpy", "all"], "description": "Linux", "update": true, "dlc": false, "hidden": false}, {"name": "mac", "formats": ["app-zip", "app-dmg"], "file_lists": ["mac", "renpy", "all"], "description": "Macintosh", "update": true, "dlc": false, "hidden": false}, {"name": "win", "formats": ["zip"], "file_lists": ["windows", "renpy", "all"], "description": "Windows", "update": true, "dlc": false, "hidden": false}, {"name": "market", "formats": ["bare-zip"], "file_lists": ["windows", "linux", "mac", "renpy", "all"], "description": "Windows, Mac, Linux for Markets", "update": true, "dlc": false, "hidden": false}, {"name": "steam", "formats": ["zip"], "file_lists": ["windows", "linux", "mac", "renpy", "all"], "description": "steam", "update": true, "dlc": false, "hidden": true}, {"name": "android", "formats": ["directory"], "file_lists": ["android", "all"], "description": "android", "update": false, "dlc": true, "hidden": true}, {"name": "ios", "formats": ["directory"], "file_lists": ["ios", "all"], "description": "ios", "update": false, "dlc": true, "hidden": true}, {"name": "web", "formats": ["zip"], "file_lists": ["web", "renpy", "all"], "description": "web", "update": false, "dlc": true, "hidden": true}], "archives": [["archive", ["all"]]], "documentation_patterns": ["*.html", "*.txt"], "base_patterns": [["*.py", null], ["*.sh", null], ["*.app/", null], ["*.dll", null], ["*.manifest", null], ["*.keystore", null], ["**.rpe.py", null], ["update.pem", null], ["lib/", null], ["renpy/", null], ["update/", null], ["common/", null], ["update/", null], ["old-game/", null], ["base/", null], ["icon.ico", null], ["icon.icns", null], ["project.json", null], ["log.txt", null], ["errors.txt", null], ["traceback.txt", null], ["image_cache.txt", null], ["text_overflow.txt", null], ["dialogue.txt", null], ["dialogue.tab", null], ["profile_screen.txt", null], ["files.txt", null], ["memory.txt", null], ["tmp/", null], ["game/saves/", null], ["game/bytecode.rpyb", null], ["archived/", null], ["launcherinfo.py", null], ["android.txt", null], ["game/presplash*.*", ["all"]], ["android.json", ["android"]], [".android.json", ["android"]], ["android-*.png", ["android"]], ["android-*.jpg", ["android"]], ["ouya_icon.png", null], ["ios-presplash.*", ["ios"]], ["ios-launchimage.png", null], ["ios-icon.png", null], ["web-presplash.png", ["web"]], ["web-presplash.jpg", ["web"]], ["web-presplash.webp", ["web"]], ["web-icon.png", ["web"]], ["progressive_download.txt", ["web"]], ["steam_appid.txt", null], ["game/cache/bytecode-39.rpyb", ["all"]], ["game/cache/bytecode-311.rpyb", ["web"]], ["game/cache/bytecode-*.rpyb", null], ["game/cache/build_info.json", null], ["game/cache/build_time.txt", null], ["**~", null], ["**.bak", null], ["**/.**", null], ["**/#**", null], ["**/thumbs.db", null], [".*", null], ["**", ["all"]]], "renpy_patterns": [["renpy/common/_compat/**", null], ["renpy/common/_roundrect/**", null], ["renpy/common/_outline/**", null], ["renpy/common/_theme**", null], ["renpy/**__pycache__/**.cpython-39.pyc", ["all"]], ["renpy/**__pycache__", ["all"]], ["**~", null], ["**/#*", null], ["**/.*", null], ["**.old", null], ["**.new", null], ["**.rpa", null], ["**.rpe", null], ["**.rpe.py", null], ["**/steam_appid.txt", null], ["renpy.py", ["all"]], ["renpy/", ["all"]], ["renpy/**.py", ["renpy"]], ["renpy/**.pxd", null], ["renpy/**.pxi", null], ["renpy/**.pyx", null], ["renpy/**.pyc", null], ["renpy/**.pyo", null], ["renpy/common/", ["all"]], ["renpy/common/_compat/**", ["renpy"]], ["renpy/common/**.rpy", ["renpy"]], ["renpy/common/**.rpym", ["renpy"]], ["renpy/common/_compat/**", ["renpy"]], ["renpy/common/**", ["all"]], ["renpy/**", ["all"]], ["lib/*/renpy", null], ["lib/*/renpy.exe", null], ["lib/*/pythonw.exe", null], ["lib/py2-*/", null], ["lib/py*-windows-i686/**", ["windows_i686"]], ["lib/py*-windows-x86_64/**", ["windows"]], ["lib/py*-linux-i686/**", ["linux_i686"]], ["lib/py*-linux-aarch64/**", ["linux_arm"]], ["lib/py*-linux-armv7l/**", ["linux_arm"]], ["lib/py*-linux-*/**", ["linux"]], ["lib/py*-mac-*/**", ["mac"]], ["lib/python2.*/**", null], ["lib/**", ["windows", "linux", "mac", "android", "ios"]], ["renpy.sh", ["linux", "mac"]]], "xbit_patterns": ["**.sh", "lib/py*-linux-*/*", "lib/py*-mac-*/*", "**.app/Contents/MacOS/*"], "version": "0.6.0alpha", "display_name": "Aperture Dating Simulator", "exclude_empty_directories": true, "allow_integrated_gpu": true, "renpy": false, "script_version": true, "destination": "ads-0.6.0alpha-dists", "itch_channels": {"*-all.zip": "win-osx-linux", "*-market.zip": "win-osx-linux", "*-pc.zip": "win-linux", "*-win.zip": "win", "*-mac.zip": "osx", "*-linux.tar.bz2": "linux", "*-release.apk": "android"}, "mac_info_plist": {}, "merge": [["linux_i686", "linux"], ["windows_i686", "windows"]], "include_i686": true, "change_icon_i686": true, "android_permissions": [], "_sdk_fonts": false, "update_formats": ["rpu"], "info": {"info": {}, "time": 1751519205.4580815, "name": "Aperture Dating Simulator", "version": "0.6.0alpha"}}}